fhir_query/__init__.py
fhir_query/aclient.py
fhir_query/aclient_test.py
fhir_query/base.py
fhir_query/bundle.py
fhir_query/bundle_test.py
fhir_query/client.py
fhir_query/client_test.py
fhir_query/constants.py
fhir_query/resource_types.py
fhir_query/utils.py
fhir_query/utils_test.py
fhir_query-0.1.2.dist-info/LICENSE
fhir_query-0.1.2.dist-info/METADATA
fhir_query-0.1.2.dist-info/WHEEL
fhir_query-0.1.2.dist-info/top_level.txt
fhir_query-0.1.2.dist-info/RECORD
