Metadata-Version: 2.2
Name: fhir-query
Version: 0.1.2
Summary: A simple client for querying FHIR servers
Requires-Python: >=3.9
License-File: LICENSE
Requires-Dist: aiohttp>=3.11.12
Requires-Dist: fhirpathpy>=1.2.1
Requires-Dist: pandas>=2.2.3
Requires-Dist: requests>=2.32.3
